pyfluent/__init__.py
pyfluent/fluent.py
pyfluentformio-0.1.3.dist-info/DESCRIPTION.rst
pyfluentformio-0.1.3.dist-info/METADATA
pyfluentformio-0.1.3.dist-info/RECORD
pyfluentformio-0.1.3.dist-info/WHEEL
pyfluentformio-0.1.3.dist-info/metadata.json
pyfluentformio-0.1.3.dist-info/top_level.txt
